MANIFEST.in
README.md
setup.py
django_papertrail.egg-info/PKG-INFO
django_papertrail.egg-info/SOURCES.txt
django_papertrail.egg-info/dependency_links.txt
django_papertrail.egg-info/requires.txt
django_papertrail.egg-info/top_level.txt
papertrail/__init__.py
papertrail/admin.py
papertrail/apps.py
papertrail/fields.py
papertrail/models.py
papertrail/signals.py
papertrail/tests.py
papertrail/migrations/0001_initial.py
papertrail/migrations/0002_auto_20160125_1711.py
papertrail/migrations/0003_message_size.py
papertrail/migrations/__init__.py
papertrail/templates/admin/change_form.html
papertrail/templates/admin/object_papertrail.html
papertrail/templatetags/__init__.py
papertrail/templatetags/papertrail.py